xdepy/__init__.py
xdepy/DBXde/XdeMysql.py
xdepy/DBXde/XdeRedis.py
xdepy/DBXde/__init__.py
xdepy/DataXde/XdeTestData.py
xdepy/DataXde/__init__.py
xdepy/MLXde/XdeTestML.py
xdepy/MLXde/__init__.py
xdepy/UtilsXde/XdeCurl.py
xdepy/UtilsXde/XdeLogger.py
xdepy/UtilsXde/XdeTestUtils.py
xdepy/UtilsXde/__init__.py
xdepy-0.0.2.dist-info/METADATA
xdepy-0.0.2.dist-info/RECORD
xdepy-0.0.2.dist-info/WHEEL
xdepy-0.0.2.dist-info/top_level.txt
