Metadata-Version: 2.1
Name: xdepy
Version: 0.0.2
Summary: a python module for quant trading by Xde
Home-page: https://github.com/xdesoft/xdepy
Author: xdexde
Author-email: zxdxinde@gmail.com
License: MIT
Platform: UNKNOWN
